prompt_template/__init__.py
prompt_template/prompt_template.py
prompt_template/py.typed
prompt_template-1.2.0.dist-info/LICENSE
prompt_template-1.2.0.dist-info/METADATA
prompt_template-1.2.0.dist-info/WHEEL
prompt_template-1.2.0.dist-info/top_level.txt
prompt_template-1.2.0.dist-info/RECORD
