Metadata-Version: 2.2
Name: prompt-template
Version: 1.2.0
Summary: A robust zero-dependency library for creating prompt templates
Author-email: Na'aman Hirschfeld <nhirschfed@gmail.com>
License: MIT
Project-URL: homepage, https://github.com/Goldziher/prompt-template
Keywords: ai,llm,prompt-engineering,prompt-template,templating
Classifier: Development Status :: 4 - Beta
Classifier: Intended Audience :: Developers
Classifier: License :: OSI Approved :: MIT License
Classifier: Operating System :: OS Independent
Classifier: Programming Language :: Python :: 3 :: Only
Classifier: Programming Language :: Python :: 3.9
Classifier: Programming Language :: Python :: 3.10
Classifier: Programming Language :: Python :: 3.11
Classifier: Programming Language :: Python :: 3.12
Classifier: Programming Language :: Python :: 3.13
Classifier: Topic :: Scientific/Engineering :: Artificial Intelligence
Classifier: Topic :: Software Development :: Libraries :: Python Modules
Classifier: Topic :: Text Processing :: General
Classifier: Topic :: Utilities
Classifier: Typing :: Typed
Requires-Python: >=3.9
License-File: LICENSE
